[{"n":"Algebra y Geometr\u00eda Anal\u00edtica","a":"1","s":"1","cd":[],"cf":[]},{"n":"C\u00e1lculo I","a":"1","s":"1","cd":[],"cf":[]},{"n":"Introducci\u00f3n a la Ingenier\u00eda en Alimentos","a":"1","s":"1","cd":[],"cf":[]},{"n":"Qu\u00edmica","a":"1","s":"1","cd":[],"cf":[]},{"n":"Computaci\u00f3n","a":"1","s":"2","cd":[],"cf":[]},{"n":"F\u00edsica I","a":"1","s":"2","cd":[2],"cf":[]},{"n":"Qu\u00edmica General e Inorg\u00e1nica","a":"1","s":"2","cd":[4],"cf":[]},{"n":"Prueba de Suficiencia en Ingl\u00e9s","a":"2","s":"Anual","cd":[],"cf":[]},{"n":"C\u00e1lculo II","a":"2","s":"1","cd":[1],"cf":[2]},{"n":"Dibujo y Sistemas de Representaci\u00f3n","a":"2","s":"1","cd":[3,5],"cf":[]},{"n":"F\u00edsica II","a":"2","s":"1","cd":[6],"cf":[1,2]},{"n":"Estad\u00edstica","a":"2","s":"2","cd":[],"cf":[2,5]},{"n":"M\u00e9todos Num\u00e9ricos","a":"2","s":"2","cd":[9],"cf":[5]},{"n":"Qu\u00edmica Org\u00e1nica","a":"2","s":"2","cd":[],"cf":[7]},{"n":"Termodin\u00e1mica Qu\u00edmica I","a":"2","s":"2","cd":[9],"cf":[3,7,6]},{"n":"Qu\u00edmica Biol\u00f3gica","a":"3","s":"1","cd":[14],"cf":[7,8]},{"n":"Tecnolog\u00eda Ambiental","a":"3","s":"1","cd":[14],"cf":[8]},{"n":"Tecnolog\u00eda de la Energ\u00eda","a":"3","s":"1","cd":[11,15],"cf":[8]},{"n":"Termodin\u00e1mica Qu\u00edmica II","a":"3","s":"1","cd":[15],"cf":[9,11,8]},{"n":"Fen\u00f3menos de Transporte","a":"3","s":"2","cd":[19],"cf":[10,15,8]},{"n":"Fisicoqu\u00edmica","a":"3","s":"2","cd":[16,19,12],"cf":[15,8]},{"n":"Materiales e Instalaciones Industriales","a":"3","s":"2","cd":[15],"cf":[6,10,8]},{"n":"Administraci\u00f3n de la Producci\u00f3n","a":"4","s":"1","cd":[],"cf":[12,8]},{"n":"Higiene y Seguridad en el Trabajo","a":"4","s":"1","cd":[18,17],"cf":[8]},{"n":"Microbiolog\u00eda General","a":"4","s":"1","cd":[21,16],"cf":[8,14]},{"n":"Operaciones Unitarias I","a":"4","s":"1","cd":[18,20,22],"cf":[8,19]},{"n":"Ingenier\u00eda Econ\u00f3mica","a":"4","s":"2","cd":[23],"cf":[8]},{"n":"Microbiolog\u00eda de los Alimentos","a":"4","s":"2","cd":[25,21],"cf":[8,16]},{"n":"Operaciones Unitarias II","a":"4","s":"2","cd":[26],"cf":[8,20,13]},{"n":"Qu\u00edmica Anal\u00edtica","a":"4","s":"2","cd":[21],"cf":[12,8]},{"n":"Proyecto de Instalaci\u00f3n Industrial","a":"5","s":"Anual","cd":[25,24,26,23,28,29,30,27],"cf":[8,17,18,22]},{"n":"Derecho y Legislaci\u00f3n","a":"5","s":"1","cd":[],"cf":[8,24]},{"n":"Ingenier\u00eda de Bioprocesos","a":"5","s":"1","cd":[28],"cf":[8,20,25,21]},{"n":"Operaciones Unitarias III","a":"5","s":"1","cd":[29],"cf":[8,26]},{"n":"Procesamiento de Alimentos I","a":"5","s":"1","cd":[28],"cf":[8,26]},{"n":"Bromatolog\u00eda","a":"5","s":"2","cd":[35],"cf":[8,28,30]},{"n":"Control de Procesos","a":"5","s":"2","cd":[34,33],"cf":[8,29]},{"n":"Ingenier\u00eda de Sistema de Proceso en la Industria Alimenticia","a":"5","s":"2","cd":[34,33],"cf":[8,29]},{"n":"Procesamiento de Alimentos II","a":"5","s":"2","cd":[35],"cf":[8,28]},{"n":"Pr\u00e1ctica Profesional","a":"5","s":"2","cd":[],"cf":[8]}]